setup.py
SBFlask/FlaskMain.py
SBFlask/__init__.py
SBFlask/run.py
SBFlask.egg-info/PKG-INFO
SBFlask.egg-info/SOURCES.txt
SBFlask.egg-info/dependency_links.txt
SBFlask.egg-info/not-zip-safe
SBFlask.egg-info/requires.txt
SBFlask.egg-info/top_level.txt
SBFlask/docs/__init__.py
SBFlask/docs/conf.py
SBFlask/tests/__init__.py
SBFlask/tests/frigged_server_responses.py