Metadata-Version: 2.1
Name: SBFlask
Version: 1.1.5
Summary: SanBlaze Flask webserver for vluns
Home-page: https://www.sanblaze.com/
Author: Matt Holsey
Author-email: mholsey@sanblaze.com
License: SanBlaze Technology ltd
Platform: UNKNOWN
